{
 "location": "United Arab Emirates",
 "updated": "2026-06-23T09:37:06.289Z",
 "count": 38,
 "vessels": [
  {
   "mmsi": 538011403,
   "name": "MARSOL SUPREME",
   "imo": 9662253,
   "flag": "🇲🇭",
   "lat": 24.6748,
   "lon": 53.3587,
   "sog": 6.9,
   "heading": 91,
   "status": "UNDERWAY"
  },
  {
   "mmsi": 355080000,
   "name": "WHITE STAR",
   "imo": 9236731,
   "flag": "🇵🇦",
   "lat": 25.5703,
   "lon": 55.136,
   "sog": 0,
   "heading": 310,
   "status": "AT ANCHOR"
  },
  {
   "mmsi": 470655000,
   "name": "AL ALIA",
   "imo": 9928956,
   "flag": "🇦🇪",
   "lat": 24.8446,
   "lon": 54.6568,
   "sog": 0,
   "heading": 146,
   "status": "RESTRICTED"
  },
  {
   "mmsi": 620999357,
   "name": "PSL TIGER",
   "imo": 9153123,
   "flag": "🇰🇲",
   "lat": 25.5136,
   "lon": 55.1766,
   "sog": 0.1,
   "heading": null,
   "status": "UNDERWAY"
  },
  {
   "mmsi": 441708000,
   "name": "PAN BONITA",
   "imo": 9626015,
   "flag": "🇰🇷",
   "lat": 25.4922,
   "lon": 55.2418,
   "sog": 0.1,
   "heading": 310,
   "status": "AT ANCHOR"
  },
  {
   "mmsi": 352257000,
   "name": "QMS AL BAHIA",
   "imo": 9828041,
   "flag": "🇵🇦",
   "lat": 24.8586,
   "lon": 53.7609,
   "sog": 0,
   "heading": 41,
   "status": "RESTRICTED"
  },
  {
   "mmsi": 636024935,
   "name": "ORINOCCO",
   "imo": 9302994,
   "flag": "🇱🇷",
   "lat": 25.7448,
   "lon": 55.1489,
   "sog": 1.3,
   "heading": 108,
   "status": "AT ANCHOR"
  },
  {
   "mmsi": 471888000,
   "name": "AL MARMAR",
   "imo": 9698513,
   "flag": "🇦🇪",
   "lat": 24.5845,
   "lon": 54.1531,
   "sog": 0,
   "heading": null,
   "status": ""
  },
  {
   "mmsi": 470588000,
   "name": "MABROKA 4",
   "imo": 9905148,
   "flag": "🇦🇪",
   "lat": 24.8169,
   "lon": 54.6448,
   "sog": 0.1,
   "heading": null,
   "status": "UNDERWAY"
  },
  {
   "mmsi": 563232600,
   "name": "PHOENIX",
   "imo": 9553232,
   "flag": "🇸🇬",
   "lat": 25.5432,
   "lon": 55.2641,
   "sog": 0.2,
   "heading": 314,
   "status": "AT ANCHOR"
  },
  {
   "mmsi": 471206000,
   "name": "BU TINAH II",
   "imo": 9985174,
   "flag": "🇦🇪",
   "lat": 24.8511,
   "lon": 54.6561,
   "sog": 7.7,
   "heading": 316,
   "status": "UNDERWAY"
  },
  {
   "mmsi": 565104000,
   "name": "BRITOIL 74",
   "imo": 9733650,
   "flag": "🇸🇬",
   "lat": 24.7978,
   "lon": 54.6542,
   "sog": 0,
   "heading": 321,
   "status": "MOORED"
  },
  {
   "mmsi": 376823000,
   "name": "OCEAN TRANSPORTER",
   "imo": 9649380,
   "flag": "🇻🇨",
   "lat": 24.687,
   "lon": 53.5558,
   "sog": 0.6,
   "heading": 69,
   "status": "SAILING"
  },
  {
   "mmsi": 470152000,
   "name": "ADNOC MP02",
   "imo": 9754329,
   "flag": "🇦🇪",
   "lat": 24.8593,
   "lon": 53.6453,
   "sog": 0,
   "heading": 304,
   "status": "RESTRICTED"
  },
  {
   "mmsi": 374667000,
   "name": "PILI PILI 4503",
   "imo": 9776298,
   "flag": "🇵🇦",
   "lat": 24.7654,
   "lon": 53.7392,
   "sog": 0,
   "heading": 36,
   "status": "MOORED"
  },
  {
   "mmsi": 352005430,
   "name": "HEA TITAN",
   "imo": 9803170,
   "flag": "🇵🇦",
   "lat": 24.8009,
   "lon": 54.2515,
   "sog": 0,
   "heading": 145,
   "status": "UNDERWAY"
  },
  {
   "mmsi": 352898675,
   "name": "QMS GLORIA",
   "imo": 9609782,
   "flag": "🇵🇦",
   "lat": 24.5166,
   "lon": 54.0638,
   "sog": 0.1,
   "heading": 42,
   "status": "MOORED"
  },
  {
   "mmsi": 538011154,
   "name": "SAFEEN OSV PEARL",
   "imo": 9594171,
   "flag": "🇲🇭",
   "lat": 24.824,
   "lon": 53.6613,
   "sog": 0,
   "heading": 29,
   "status": "RESTRICTED"
  },
  {
   "mmsi": 350139000,
   "name": "BINARY STAR",
   "imo": 9380570,
   "flag": "🇳🇮",
   "lat": 25.5876,
   "lon": 55.1353,
   "sog": 0,
   "heading": 306,
   "status": "AT ANCHOR"
  },
  {
   "mmsi": 577723000,
   "name": "ZIXUAN",
   "imo": 9317298,
   "flag": "🇻🇺",
   "lat": 25.6426,
   "lon": 55.1157,
   "sog": 0.1,
   "heading": 302,
   "status": "AT ANCHOR"
  },
  {
   "mmsi": 236112762,
   "name": "HERCULES COMET",
   "imo": 9825087,
   "flag": "🇬🇮",
   "lat": 25.5024,
   "lon": 55.2377,
   "sog": 7.2,
   "heading": 275,
   "status": "UNDERWAY"
  },
  {
   "mmsi": 470125000,
   "name": "AL MARYAH-1",
   "imo": 9817420,
   "flag": "🇦🇪",
   "lat": 24.7934,
   "lon": 54.6912,
   "sog": 0,
   "heading": null,
   "status": "SAILING"
  },
  {
   "mmsi": 470311000,
   "name": "DAS-1",
   "imo": 9817432,
   "flag": "🇦🇪",
   "lat": 24.8455,
   "lon": 54.6598,
   "sog": 7,
   "heading": null,
   "status": ""
  },
  {
   "mmsi": 470471000,
   "name": "AL DURRAH",
   "imo": 9647368,
   "flag": "🇦🇪",
   "lat": 24.7931,
   "lon": 54.6927,
   "sog": 0.4,
   "heading": 355,
   "status": "MOORED"
  },
  {
   "mmsi": 720017000,
   "name": "MIDAS 7",
   "imo": 1134420,
   "flag": "🇧🇴",
   "lat": 25.5729,
   "lon": 55.2817,
   "sog": 8.3,
   "heading": 4,
   "status": "AT ANCHOR"
  },
  {
   "mmsi": 477931100,
   "name": "MAPLE UNITY",
   "imo": 9605011,
   "flag": "🇭🇰",
   "lat": 25.7146,
   "lon": 55.1274,
   "sog": 2.2,
   "heading": 271,
   "status": "UNDERWAY"
  },
  {
   "mmsi": 470011000,
   "name": "ADNOC 226",
   "imo": 9725249,
   "flag": "🇦🇪",
   "lat": 24.5428,
   "lon": 54.0324,
   "sog": 7.1,
   "heading": 330,
   "status": "UNDERWAY"
  },
  {
   "mmsi": 372086000,
   "name": "KAWAWA 4304",
   "imo": 8769468,
   "flag": "🇵🇦",
   "lat": 24.8595,
   "lon": 53.6147,
   "sog": 0.1,
   "heading": 143,
   "status": "MOORED"
  },
  {
   "mmsi": 564465000,
   "name": "CREST RADIANT 5",
   "imo": 9535369,
   "flag": "🇸🇬",
   "lat": 24.5158,
   "lon": 54.025,
   "sog": 0.3,
   "heading": 224,
   "status": "UNDERWAY"
  },
  {
   "mmsi": 244810054,
   "name": "JUMBO KINETIC",
   "imo": 9634165,
   "flag": "🇳🇱",
   "lat": 24.8554,
   "lon": 54.6521,
   "sog": 7.8,
   "heading": 321,
   "status": "MOORED"
  },
  {
   "mmsi": 471201000,
   "name": "ESHRAQ",
   "imo": 1075193,
   "flag": "🇦🇪",
   "lat": 24.6951,
   "lon": 53.7617,
   "sog": 5.1,
   "heading": 101,
   "status": "UNDERWAY"
  },
  {
   "mmsi": 629009484,
   "name": "BILI",
   "imo": 9285756,
   "flag": "🇬🇲",
   "lat": 25.8533,
   "lon": 56.9417,
   "sog": 0.1,
   "heading": 97,
   "status": "AT ANCHOR"
  },
  {
   "mmsi": 248139000,
   "name": "TRANSSHELF",
   "imo": 8512279,
   "flag": "🇲🇹",
   "lat": 25.4772,
   "lon": 55.2084,
   "sog": 0,
   "heading": 321,
   "status": "AT ANCHOR"
  },
  {
   "mmsi": 470022000,
   "name": "RIG YAS",
   "imo": 9709996,
   "flag": "🇦🇪",
   "lat": 24.828,
   "lon": 53.5729,
   "sog": 0.1,
   "heading": null,
   "status": ""
  },
  {
   "mmsi": 471008764,
   "name": "DELMA 14",
   "imo": null,
   "flag": "🇦🇪",
   "lat": 24.8343,
   "lon": 54.6458,
   "sog": 0,
   "heading": null,
   "status": ""
  },
  {
   "mmsi": 374448000,
   "name": "BUNUN MIRACLE",
   "imo": 9867372,
   "flag": "🇵🇦",
   "lat": 25.5087,
   "lon": 55.1885,
   "sog": 7.6,
   "heading": 245,
   "status": "UNDERWAY"
  },
  {
   "mmsi": 636015376,
   "name": "NOBLE MICK OBRIEN",
   "imo": 8771239,
   "flag": "🇱🇷",
   "lat": 24.808,
   "lon": 54.663,
   "sog": 0,
   "heading": null,
   "status": "MOORED"
  },
  {
   "mmsi": 566558000,
   "name": "POSH ENTERPRISE",
   "imo": 9722211,
   "flag": "🇸🇬",
   "lat": 24.9197,
   "lon": 54.5584,
   "sog": 0,
   "heading": 302,
   "status": "AT ANCHOR"
  }
 ]
}